[
  {
    "name": "charensol",
    "url": "https://intranet.iut-valence.fr/img/PhotosPersonnel/45267.jpg",
    "citations": [
      "Il y a que les imbéciles qui ne changent pas d'avis ",
      "Domage que tu ne soit plus délégué hein?"
    ]
  },
  {
    "name": "medge",
    "url": "https://intranet.iut-valence.fr/img/PhotosPersonnel/42000.jpg",
    "citations": [
      "Oh les geek on range le matos????",
      "tu vois la chaussure ? Elle pourrait rentrer dans ton....."
    ]
  },
  {
    "name": "genthial",
    "url": "https://intranet.iut-valence.fr/img/PhotosPersonnel/40323.jpg",
    "citations": [
      "Après il y a la loi et l’application de la loi !"
    ]
  },
  {
    "name": "objois",
    "url": "https://intranet.iut-valence.fr/img/PhotosPersonnel/40524.jpg",
    "citations": [
      "DEHOOOOOOOOOOOOOOOOORS !"
    ]
  },
  {
    "name": "occelo",
    "url": "https://intranet.iut-valence.fr/img/PhotosPersonnel/41069.jpg",
    "citations": [
      "Je vous ai schouinté"
    ]
  },
  {
    "name": "boulle",
    "url": "https://intranet.iut-valence.fr/img/PhotosPersonnel/43636.jpg",
    "citations": [
      "Je ne sais pas ce que vous faites sous la table "
    ]
  },
  {
    "name": "antoine",
    "url": "https://intranet.iut-valence.fr/img/PhotosEtudiants/berthil1.jpg",
    "citations": [
      "Hiii Hiii Hiiii *rire de démon*"
    ]
  },
  {
    "name": "blandine",
    "url": "https://purepng.com/public/uploads/medium/purepng.com-clownsclowncomedytraditionredclowndistinctive-makeupcolourful-wigscolourful-clothingclipart-1421526854624l86di.png",
    "citations": [
      "Les îles Féréro",
      "Il va falloir que jpasse sous la taaaaaaaable",
      "Mathys range moi ce truc 😏",
      "Tu fumes pas un peu des joins sabri? Il a deux de tension",
      "Nan mais c'est bien il ne moura pas d'hypertension",
      "Alors Yohann comment ça c'est passé tes vacances ? Tu m'as pas raconté"
    ]
  },
  {
    "name": "desauza",
    "url": "https://intranet.iut-valence.fr/img/PhotosPersonnel/44742.jpg",
    "citations": [
      "Théo je suis ton père"
    ]
  },
  {
    "name": "yohann",
    "url": "https://intranet.iut-valence.fr/img/PhotosEtudiants/chavaney.jpg",
    "citations": [
      "Qu'est-ce que Ethan un matin à 8h en excès de vitesse sur le périph' ? -> Un con-pressé ! ",
      "On a des idées originales"
    ]
  },
  {
    "name": "leo",
    "urm": "https://intranet.iut-valence.fr/img/PhotosEtudiants/deroinl.jpg",
    "citations": [
      "Nan mais attends on a suivi le cours avec Lucci, jécoutais de la musique moi",
      "Tu rigoles mais j'ai onlyfans mdr",
      "houla j'ai fait un gros zoom sur son magnifique engin"
    ]
  }
]